win2utc/__init__.py
win2utc/cli.py
win2utc/converter.py
win2utc/data/timezones.json
win2utc/data/windowsZones.xml
win2utc-0.2.0.dist-info/licenses/LICENSE
win2utc-0.2.0.dist-info/METADATA
win2utc-0.2.0.dist-info/WHEEL
win2utc-0.2.0.dist-info/entry_points.txt
win2utc-0.2.0.dist-info/top_level.txt
win2utc-0.2.0.dist-info/RECORD
